suid_machine/__init__.py
suid_machine/client.py
suid_machine/interface.py
suid_machine/machine.py
suid_machine/server.py
suid_machine-0.1.0.dist-info/METADATA
suid_machine-0.1.0.dist-info/WHEEL
suid_machine-0.1.0.dist-info/RECORD
